LICENSE
flake8_markdown/__init__.py
flake8_markdown/__main__.py
flake8_markdown/constants.py
flake8_markdown-0.2.0.dist-info/entry_points.txt
flake8_markdown-0.2.0.dist-info/LICENSE
flake8_markdown-0.2.0.dist-info/WHEEL
flake8_markdown-0.2.0.dist-info/METADATA
flake8_markdown-0.2.0.dist-info/RECORD
