Metadata-Version: 2.1
Name: flake8-markdown
Version: 0.2.0
Summary: Lints Python code blocks in Markdown files using flake8
Home-page: https://github.com/johnfraney/flake8-markdown
License: MIT
Keywords: flake8,markdown,lint
Author: John Franey
Author-email: johnfraney@gmail.com
Requires-Python: >=3.6,<4.0
Classifier: Environment :: Console
Classifier: Framework :: Flake8
Classifier: License :: OSI Approved :: MIT License
Classifier: Operating System :: OS Independent
Classifier: Programming Language :: Python :: 3
Classifier: Programming Language :: Python :: 3.6
Classifier: Programming Language :: Python :: 3.7
Classifier: Topic :: Software Development :: Documentation
Classifier: Topic :: Software Development :: Libraries :: Python Modules
Classifier: Topic :: Software Development :: Quality Assurance
Requires-Dist: flake8 (>=3.7,<4.0)
Project-URL: Repository, https://github.com/johnfraney/flake8-markdown
